funapi/__init__.py
fun1688-0.0.1.dist-info/LICENSE
fun1688-0.0.1.dist-info/METADATA
fun1688-0.0.1.dist-info/WHEEL
fun1688-0.0.1.dist-info/entry_points.txt
fun1688-0.0.1.dist-info/top_level.txt
fun1688-0.0.1.dist-info/RECORD
