Metadata-Version: 2.1
Name: fun1688
Version: 0.0.1
Summary: fun1688
Home-page: https://github.com/farfarfun/fun1688
Author: bingtao
Author-email: 1007530194@qq.com
License-File: LICENSE
Requires-Dist: funpypi
Requires-Dist: funfile
Requires-Dist: requests
Requires-Dist: tqdm
